morris/__init__.py
morris/fields.py
morris/widgets.py
morris/static/morris/js/hex_color.js
morris/static/morris/js/hex_color.min.js
morris/templates/morris/hex_color.html
django_morris-0.2.1.dist-info/LICENSE.txt
django_morris-0.2.1.dist-info/METADATA
django_morris-0.2.1.dist-info/WHEEL
django_morris-0.2.1.dist-info/top_level.txt
django_morris-0.2.1.dist-info/RECORD
